gdrfile/__init__.py
gdrfile/__main__.py
gdrfile/generate_sample.py
gdrfile/generations/__init__.py
gdrfile/generations/admin.py
gdrfile/generations/conftest.py
gdrfile/generations/init_serializers.py
gdrfile/generations/init_views.py
gdrfile/generations/routers.py
gdrfile/generations/rules.py
gdrfile/generations/serializers.py
gdrfile/generations/tests.py
gdrfile/generations/views.py
gdrfile/generations/views_this_rules.py
gdrfile/helpers/__init__.py
gdrfile/helpers/analysis_file_model.py
gdrfile/helpers/helper.py
gdrfile/helpers/preparation.py
gdrfile/main.py
gdrfile/sample/conftest/conftest_factory.py
gdrfile/sample/conftest/conftest_fixture.py
gdrfile/sample/conftest/conftest_import.py
gdrfile/sample/example_admin.py
gdrfile/sample/example_init_serializer.py
gdrfile/sample/example_init_view.py
gdrfile/sample/example_routers.py
gdrfile/sample/example_rules.py
gdrfile/sample/example_serializers.py
gdrfile/sample/example_tests.py
gdrfile/sample/example_views.py
gdrfile/sample/example_views_this_rules.py
gdrfile-0.0.1.dist-info/entry_points.txt
gdrfile-0.0.1.dist-info/LICENSE
gdrfile-0.0.1.dist-info/WHEEL
gdrfile-0.0.1.dist-info/METADATA
gdrfile-0.0.1.dist-info/RECORD
