Metadata-Version: 2.1
Name: gdrfile
Version: 0.0.1
Summary: Generate file for django rest framework.
Home-page: https://github.com/BigBread57/gdrfile
License: MIT
Author: Gleb Mazur
Author-email: mazur.gleb2010@yandex.ru
Requires-Python: >=3.7,<4
Classifier: License :: OSI Approved :: MIT License
Classifier: Programming Language :: Python :: 3
Classifier: Programming Language :: Python :: 3.10
Classifier: Programming Language :: Python :: 3.7
Classifier: Programming Language :: Python :: 3.8
Classifier: Programming Language :: Python :: 3.9
Requires-Dist: poetry-core (>=1.0.8,<2.0.0)
Requires-Dist: python-dotenv (>=0.20.0,<0.21.0)
Project-URL: Repository, https://github.com/BigBread57/gdrfile
